degiroapi/__init__.py
degiroapi/__version__.py
degiroapi/client_info.py
degiroapi/data_type.py
degiroapi/degiro.py
degiroapi/exceptions.py
degiroapi/interval_type.py
degiroapi/order_type.py
degiroapi/product.py
degiroapi/utils.py
python_degiro-0.1.0.dist-info/LICENSE
python_degiro-0.1.0.dist-info/METADATA
python_degiro-0.1.0.dist-info/WHEEL
python_degiro-0.1.0.dist-info/top_level.txt
python_degiro-0.1.0.dist-info/RECORD
