Metadata-Version: 2.1
Name: python-degiro
Version: 0.1.0
Summary: An unofficial API for the trading platform DeGiro written in Python
Home-page: https://github.com/Jorricks/python-degiro
Author: Jorrick Sleijster
Author-email: jorricks3@gmail.com
License: UNKNOWN
Platform: UNKNOWN
Classifier: Programming Language :: Python :: 3
Classifier: License :: OSI Approved :: MIT License
Classifier: Operating System :: OS Independent
Requires-Python: >=3.6
License-File: LICENSE
Requires-Dist: requests (>=2.0.0)
Provides-Extra: devel
Requires-Dist: black (==21.6b0) ; extra == 'devel'
Requires-Dist: flake8 (==3.9.2) ; extra == 'devel'
Requires-Dist: isort (==5.9.3) ; extra == 'devel'
Requires-Dist: mypy (==0.910) ; extra == 'devel'
Requires-Dist: mypy-extensions (==0.4.3) ; extra == 'devel'
Requires-Dist: typing-extensions (==3.10.0.0) ; extra == 'devel'
Requires-Dist: pytest (==6.2.4) ; extra == 'devel'
Requires-Dist: pytest-cov (==2.12.1) ; extra == 'devel'
Requires-Dist: pre-commit (==2.13.0) ; extra == 'devel'
Requires-Dist: pydocstyle (==5.1.1) ; extra == 'devel'
Provides-Extra: lint
Requires-Dist: black (==21.6b0) ; extra == 'lint'
Requires-Dist: flake8 (==3.9.2) ; extra == 'lint'
Requires-Dist: isort (==5.9.3) ; extra == 'lint'
Provides-Extra: mypy
Requires-Dist: mypy (==0.910) ; extra == 'mypy'
Requires-Dist: mypy-extensions (==0.4.3) ; extra == 'mypy'
Requires-Dist: typing-extensions (==3.10.0.0) ; extra == 'mypy'
Provides-Extra: prec
Requires-Dist: pre-commit (==2.13.0) ; extra == 'prec'
Requires-Dist: pydocstyle (==5.1.1) ; extra == 'prec'
Provides-Extra: test
Requires-Dist: pytest (==6.2.4) ; extra == 'test'
Requires-Dist: pytest-cov (==2.12.1) ; extra == 'test'
